<stix:STIX_Package
	xmlns:ta="http://stix.mitre.org/ThreatActor-1"
	xmlns:stixCommon="http://stix.mitre.org/common-1"
	xmlns:stix="http://stix.mitre.org/stix-1"
	xmlns:campaign="http://stix.mitre.org/Campaign-1"
	xmlns:example="http://example.com"
	xmlns:xlink="http://www.w3.org/1999/xlink"
	xmlns:ds="http://www.w3.org/2000/09/xmldsig#"
	xmlns:xs="http://www.w3.org/2001/XMLSchema"
	xmlns:xsi="http://www.w3.org/2001/XMLSchema-instance"
	 id="example:STIXPackage-81810123-b298-40f6-a4e7-186efcd07670" version="1.2">
    <stix:Campaigns>
        <stix:Campaign id="example:campaign-e5268b6e-4931-42f1-b379-87f48eb41b1e" timestamp="2014-08-08T15:50:10.983000+00:00" xsi:type='campaign:CampaignType'>
            <campaign:Title>Compromise of ATM Machines</campaign:Title>
            <campaign:Description>Fred</campaign:Description>
            <campaign:Names>
                <campaign:Name>Charming Kittens</campaign:Name>
                <campaign:Name>NewsBeef</campaign:Name>
            </campaign:Names>
            <campaign:Information_Source>
                <stixCommon:References>
                    <stixCommon:Reference>http://foo.com/bar</stixCommon:Reference>
                </stixCommon:References>
            </campaign:Information_Source>
        </stix:Campaign>
    </stix:Campaigns>
    <stix:Threat_Actors>
        <stix:Threat_Actor id="example:threat-actor-56f3f0db-b5d5-431c-ae56-c18f02caf500" timestamp="2014-08-08T15:50:10.983000+00:00" xsi:type='ta:ThreatActorType'>
            <ta:Title>People behind the intrusion</ta:Title>
            <ta:Type timestamp="2021-08-11T20:57:43.355758+00:00">
                <stixCommon:Value>unknown</stixCommon:Value>
            </ta:Type>
            <ta:Sophistication timestamp="2021-08-11T20:57:43.355795+00:00">
                <stixCommon:Value>unknown</stixCommon:Value>
            </ta:Sophistication>
            <ta:Associated_Campaigns>
                <ta:Associated_Campaign>
                    <stixCommon:Campaign idref="example:campaign-e5268b6e-4931-42f1-b379-87f48eb41b1e" xsi:type='campaign:CampaignType'/>
                </ta:Associated_Campaign>
            </ta:Associated_Campaigns>
        </stix:Threat_Actor>
    </stix:Threat_Actors>
</stix:STIX_Package>